ga_api/__init__.py
ga_api/average.py
ga_api/capture.py
ga_api/field_tree.py
ga_api/ga_api_client.py
ga_api/hyper_log_log.py
ga_api/rate.py
ga_api/std.py
ga_api/tdigest.py
ga_api_client-0.6.6.dist-info/licenses/LICENSE
ga_api_client-0.6.6.dist-info/METADATA
ga_api_client-0.6.6.dist-info/WHEEL
ga_api_client-0.6.6.dist-info/top_level.txt
ga_api_client-0.6.6.dist-info/RECORD
