Metadata-Version: 2.4
Name: ga-api-client
Version: 0.6.6
Classifier: Programming Language :: Python :: 3
Classifier: License :: OSI Approved :: MIT License
Classifier: Operating System :: OS Independent
Requires-Python: >=3.9
License-File: LICENSE
Requires-Dist: pandas>=1.4
Requires-Dist: aiohttp>=3.8
Requires-Dist: cryptography>=36.0
Requires-Dist: async-timeout>=5.0
Dynamic: license-file
